wavestate/model/__init__.py
wavestate/model/_base.py
wavestate/model/_version.py
wavestate/model/optics1064.py
wavestate/model/base/__init__.py
wavestate/model/base/dictionary_keys.py
wavestate/model/base/frequency.py
wavestate/model/base/frequency_keys.py
wavestate/model/base/keygroups.py
wavestate/model/base/optical_frequency.py
wavestate/model/base/port_types.py
wavestate/model/base/simulation_object.py
wavestate/model/base/units.py
wavestate/model/optics/__init__.py
wavestate/model/optics/circulator.py
wavestate/model/optics/laser.py
wavestate/model/optics/marker.py
wavestate/model/optics/mirror.py
wavestate/model/optics/mode_matching.py
wavestate/model/optics/optical_frequency.py
wavestate/model/optics/photodiode.py
wavestate/model/optics/simple_modulators.py
wavestate/model/optics/space.py
wavestate/model/optics/squeezer.py
wavestate/model/optics/substrate_lens.py
wavestate/model/optics/thin_lens.py
wavestate/model/optics/vacuum.py
wavestate/model/optics/alm/__init__.py
wavestate/model/optics/alm/beam_fit.py
wavestate/model/optics/alm/beam_param.py
wavestate/model/optics/alm/substrates.py
wavestate/model/optics/alm/utils.py
wavestate/model/optics/test/test_FP.py
wavestate/model/pgraph/__init__.py
wavestate/model/pgraph/p_graph.py
wavestate/model/pgraph/p_graph_impl.py
wavestate/model/pgraph/p_graph_symbolics.py
wavestate/model/pgraph/p_object.py
wavestate/model/pgraph/p_object_schemas.py
wavestate/model/pgraph/utilities.py
wavestate/model/pgraph/test/test_pgraph.py
wavestate/model/pytest/__init__.py
wavestate/model/registry/__init__.py
wavestate/model/registry/loader.py
wavestate/model/system/__init__.py
wavestate/model/system/algo_AC.py
wavestate/model/system/algo_DC.py
wavestate/model/system/algo_bg.py
wavestate/model/system/algo_freq.py
wavestate/model/system/algo_graphs.py
wavestate/model/system/algo_link.py
wavestate/model/system/algo_log.py
wavestate/model/system/algo_phys.py
wavestate/model/system/algo_tups.py
wavestate.model-0.1.1.dist-info/METADATA
wavestate.model-0.1.1.dist-info/NOTICE
wavestate.model-0.1.1.dist-info/WHEEL
wavestate.model-0.1.1.dist-info/top_level.txt
wavestate.model-0.1.1.dist-info/RECORD
