Metadata-Version: 2.1
Name: wavestate.model
Version: 0.1.1
Summary: System description and simulation processing for interferometers, circuits, signals, and control systems
Home-page: https://github.com/wavestate/wavestate-model
Author: Lee McCuller
Author-email: mcculler@mit.edu
License: Apache-2.0
Project-URL: Bug Tracker, https://github.com/wavestate/wavestate-model/issues
Project-URL: Source Code, https://github.com/wavestate/wavestate-model
Platform: UNKNOWN
Classifier: Intended Audience :: Science/Research
Classifier: License :: OSI Approved :: Apache Software License
Classifier: Operating System :: OS Independent
Classifier: Programming Language :: Python
Classifier: Programming Language :: Python :: 3
Classifier: Topic :: Scientific/Engineering :: Physics
License-File: LICENSES/Apache-2.0.txt
License-File: LICENSES/CC0-1.0.txt
License-File: NOTICE
Requires-Dist: wavestate.bunch (>=0.9.1)
Requires-Dist: wavestate.declarative (>=1.3.3)
Requires-Dist: wavestate.utilities (>=0.9.1)
Requires-Dist: PyYAML
Requires-Dist: numpy
Requires-Dist: scipy
Requires-Dist: matplotlib
